README.md
setup.py
CarvePi/main.py
CarvePi/setup.py
CarvePi.egg-info/PKG-INFO
CarvePi.egg-info/SOURCES.txt
CarvePi.egg-info/dependency_links.txt
CarvePi.egg-info/not-zip-safe
CarvePi.egg-info/top_level.txt